__init__.py
test/__init__.py
test/main.py
spark_wheel_test-0.0.1.dist-info/LICENSE
spark_wheel_test-0.0.1.dist-info/METADATA
spark_wheel_test-0.0.1.dist-info/WHEEL
spark_wheel_test-0.0.1.dist-info/top_level.txt
spark_wheel_test-0.0.1.dist-info/RECORD
